models/__init__.py
models/cnn-simple-model-1560191984.1229792.h5
models/cnn-simple-model-1560265830.333636.h5
models/cnn-simple-model.json
src/__init__.py
src/cli.py
src/crystal_processing/__init__.py
src/crystal_processing/process_image_folder.py
src/data/__init__.py
src/data/compare_segmentation.py
src/data/segment_droplets.py
src/data/utils.py
src/models/__init__.py
src/models/train/__init__.py
src/models/train/cnn_on_vgg16_bottleneck.py
src/models/train/cnn_simple.py
src/models/train/cnn_transfer.py
src/models/utils/__init__.py
src/models/utils/loading_models.py
src/models/utils/predict_from_model.py
src/visualization/__init__.py
src/visualization/image_processing_overlay.py
src/visualization/process_plotting.py
src/visualization/training_plot.py
crystalml-0.1.1.dist-info/LICENSE
crystalml-0.1.1.dist-info/METADATA
crystalml-0.1.1.dist-info/WHEEL
crystalml-0.1.1.dist-info/entry_points.txt
crystalml-0.1.1.dist-info/top_level.txt
crystalml-0.1.1.dist-info/RECORD
