Metadata-Version: 2.1
Name: crystalml
Version: 0.1.1
Summary: Integrated tool to measure the nucleation rate of protein crystals. 
Home-page: https://github.com/hlgirard/CrystalML
Author: Henri-Louis Girard
Author-email: hl.girard@gmail.com
License: GPLv3
Platform: UNKNOWN
Requires-Dist: click
Requires-Dist: bleach (>=2.1.0)
Requires-Dist: docutils (>=0.13.1)
Requires-Dist: Pygments
Requires-Dist: tensorflow
Requires-Dist: matplotlib
Requires-Dist: numpy
Requires-Dist: opencv-python
Requires-Dist: pkginfo (>=1.4.2)
Requires-Dist: pandas
Requires-Dist: joblib
Requires-Dist: pillow (>=6.2.0)
Requires-Dist: plotly
Requires-Dist: scikit-image
Requires-Dist: setuptools
Requires-Dist: scipy
Requires-Dist: seaborn
Requires-Dist: tensorboard
Requires-Dist: tqdm
